odoo8_addon_base_ubl-8.0.1.1.0-nspkg.pth
odoo_addons/base_ubl/README.rst
odoo_addons/base_ubl/__init__.py
odoo_addons/base_ubl/__openerp__.py
odoo_addons/base_ubl/data/xsd-2.0/common/CCTS_CCT_SchemaModule-2.0.xsd
odoo_addons/base_ubl/data/xsd-2.0/common/CodeList_CurrencyCode_ISO_7_04.xsd
odoo_addons/base_ubl/data/xsd-2.0/common/CodeList_LanguageCode_ISO_7_04.xsd
odoo_addons/base_ubl/data/xsd-2.0/common/CodeList_MIMEMediaTypeCode_IANA_7_04.xsd
odoo_addons/base_ubl/data/xsd-2.0/common/CodeList_UnitCode_UNECE_7_04.xsd
odoo_addons/base_ubl/data/xsd-2.0/common/UBL-CommonAggregateComponents-2.0.xsd
odoo_addons/base_ubl/data/xsd-2.0/common/UBL-CommonBasicComponents-2.0.xsd
odoo_addons/base_ubl/data/xsd-2.0/common/UBL-CommonExtensionComponents-2.0.xsd
odoo_addons/base_ubl/data/xsd-2.0/common/UBL-CoreComponentParameters-2.0.xsd
odoo_addons/base_ubl/data/xsd-2.0/common/UBL-ExtensionContentDatatype-2.0.xsd
odoo_addons/base_ubl/data/xsd-2.0/common/UBL-QualifiedDatatypes-2.0.xsd
odoo_addons/base_ubl/data/xsd-2.0/common/UnqualifiedDataTypeSchemaModule-2.0.xsd
odoo_addons/base_ubl/data/xsd-2.0/maindoc/UBL-ApplicationResponse-2.0.xsd
odoo_addons/base_ubl/data/xsd-2.0/maindoc/UBL-AttachedDocument-2.0.xsd
odoo_addons/base_ubl/data/xsd-2.0/maindoc/UBL-BillOfLading-2.0.xsd
odoo_addons/base_ubl/data/xsd-2.0/maindoc/UBL-Catalogue-2.0.xsd
odoo_addons/base_ubl/data/xsd-2.0/maindoc/UBL-CatalogueDeletion-2.0.xsd
odoo_addons/base_ubl/data/xsd-2.0/maindoc/UBL-CatalogueItemSpecificationUpdate-2.0.xsd
odoo_addons/base_ubl/data/xsd-2.0/maindoc/UBL-CataloguePricingUpdate-2.0.xsd
odoo_addons/base_ubl/data/xsd-2.0/maindoc/UBL-CatalogueRequest-2.0.xsd
odoo_addons/base_ubl/data/xsd-2.0/maindoc/UBL-CertificateOfOrigin-2.0.xsd
odoo_addons/base_ubl/data/xsd-2.0/maindoc/UBL-CreditNote-2.0.xsd
odoo_addons/base_ubl/data/xsd-2.0/maindoc/UBL-DebitNote-2.0.xsd
odoo_addons/base_ubl/data/xsd-2.0/maindoc/UBL-DespatchAdvice-2.0.xsd
odoo_addons/base_ubl/data/xsd-2.0/maindoc/UBL-ForwardingInstructions-2.0.xsd
odoo8_addon_base_ubl-8.0.1.1.0.dist-info/METADATA
odoo8_addon_base_ubl-8.0.1.1.0.dist-info/WHEEL
odoo8_addon_base_ubl-8.0.1.1.0.dist-info/namespace_packages.txt
odoo8_addon_base_ubl-8.0.1.1.0.dist-info/top_level.txt
odoo8_addon_base_ubl-8.0.1.1.0.dist-info/RECORD
